mccurse/__init__.py
mccurse/__main__.py
mccurse/addon.py
mccurse/cli.py
mccurse/curse.py
mccurse/exceptions.py
mccurse/pack.py
mccurse/proxy.py
mccurse/tui.py
mccurse/_data_/supported_games.yaml
mccurse/util/__init__.py
mccurse/util/cerberus.py
mccurse/util/yaml.py
mccurse-0.5.1.dist-info/DESCRIPTION.rst
mccurse-0.5.1.dist-info/METADATA
mccurse-0.5.1.dist-info/RECORD
mccurse-0.5.1.dist-info/WHEEL
mccurse-0.5.1.dist-info/entry_points.txt
mccurse-0.5.1.dist-info/metadata.json
mccurse-0.5.1.dist-info/top_level.txt
