Metadata-Version: 2.0
Name: mccurse
Version: 0.5.1
Summary: Minecraft Curse CLI Client
Home-page: https://github.com/khardix/mccurse
Author: Jan "Khardix" Staněk
Author-email: khardix@gmail.com
License: AGPLv3+
Keywords: minecraft modding automation
Platform: UNKNOWN
Classifier: Development Status :: 4 - Beta
Classifier: Intended Audience :: End Users/Desktop
Classifier: Topic :: Games/Entertainment
Classifier: Topic :: Utilities
Classifier: License :: OSI Approved :: GNU Affero General Public License v3 or later (AGPLv3+)
Classifier: Programming Language :: Python :: 3 :: Only
Classifier: Programming Language :: Python :: 3.5
Classifier: Programming Language :: Python :: 3.6
Requires-Dist: attrs (<18,>=17)
Requires-Dist: click
Requires-Dist: cerberus
Requires-Dist: colorlog
Requires-Dist: ijson
Requires-Dist: iso8601
Requires-Dist: pyyaml
Requires-Dist: pyxdg
Requires-Dist: requests
Requires-Dist: sqlalchemy
Requires-Dist: urwid
Provides-Extra: test
Requires-Dist: betamax; extra == 'test'
Requires-Dist: pyfakefs; extra == 'test'
Requires-Dist: pytest; extra == 'test'
Requires-Dist: pytest-lazy-fixture; extra == 'test'
Requires-Dist: responses; extra == 'test'
Requires-Dist: tox; extra == 'test'
